code_generator/__init__.py
code_generator/cli.py
code_generator_odin-0.1.2.dist-info/METADATA
code_generator_odin-0.1.2.dist-info/WHEEL
code_generator_odin-0.1.2.dist-info/entry_points.txt
code_generator_odin-0.1.2.dist-info/top_level.txt
code_generator_odin-0.1.2.dist-info/RECORD
